qcpy/__init__.py
qcpy/circuit_drawing/__init__.py
qcpy/circuit_drawing/circuit_drawing.py
qcpy/circuit_drawing/drawings.py
qcpy/circuit_drawing/wire.py
qcpy/errors/__init__.py
qcpy/quantum_circuit/__init__.py
qcpy/quantum_circuit/quantum_circuit.py
qcpy/quantum_circuit/base/__init__.py
qcpy/quantum_circuit/base/base_calculator.py
qcpy/quantum_circuit/base/base_core.py
qcpy/quantum_circuit/base/base_multi_gate.py
qcpy/quantum_circuit/base/base_single_gate.py
qcpy/quantum_circuit/gpu/__init__.py
qcpy/quantum_circuit/gpu/gpu_calculator.py
qcpy/quantum_circuit/gpu/gpu_core.py
qcpy/quantum_circuit/gpu/gpu_multi_gate.py
qcpy/quantum_circuit/gpu/gpu_single_gate.py
qcpy/quantum_circuit/gpu_sparse/__init__.py
qcpy/quantum_circuit/gpu_sparse/gpu_sparse_calculator.py
qcpy/quantum_circuit/gpu_sparse/gpu_sparse_core.py
qcpy/quantum_circuit/gpu_sparse/gpu_sparse_multi_gate.py
qcpy/quantum_circuit/gpu_sparse/gpu_sparse_single_gate.py
qcpy/quantum_circuit/interface/__init__.py
qcpy/quantum_circuit/interface/calculator_interface.py
qcpy/quantum_circuit/interface/core_interface.py
qcpy/quantum_circuit/interface/multi_gate_interface.py
qcpy/quantum_circuit/interface/single_gate_interface.py
qcpy/quantum_circuit/sparse/__init__.py
qcpy/quantum_circuit/sparse/sparse_calculator.py
qcpy/quantum_circuit/sparse/sparse_core.py
qcpy/quantum_circuit/sparse/sparse_multi_gate.py
qcpy/quantum_circuit/sparse/sparse_single_gate.py
qcpy/quantum_gate/__init__.py
qcpy/quantum_gate/gates.py
qcpy/qubit/__init__.py
qcpy/qubit/qubit.py
qcpy/tools/__init__.py
qcpy/tools/amplitude.py
qcpy/tools/measure.py
qcpy/tools/phase_angle.py
qcpy/tools/probability.py
qcpy/tools/base/__init__.py
qcpy/tools/base/convert_state.py
qcpy/visualize/__init__.py
qcpy/visualize/bloch.py
qcpy/visualize/probability.py
qcpy/visualize/q_sphere.py
qcpy/visualize/state_vector.py
qcpy/visualize/base/__init__.py
qcpy/visualize/base/color_bar.py
qcpy/visualize/base/graph.py
qcpy/visualize/base/light_mode.py
qcpydev-1.1.2rc0.dist-info/LICENSE.txt
qcpydev-1.1.2rc0.dist-info/METADATA
qcpydev-1.1.2rc0.dist-info/WHEEL
qcpydev-1.1.2rc0.dist-info/top_level.txt
qcpydev-1.1.2rc0.dist-info/RECORD
