Metadata-Version: 2.1
Name: qcpydev
Version: 1.1.2rc0
Summary: qcpy is an open source python library and collaborative project for flexible simulations and visualizations of quantum circuits.
Home-page: https://github.com/QCpython/qcpy
Author: Brennan Freeze, Paris Osuch, Aundre Barras
Author-email: freezebrennan@gmail.com
Classifier: Programming Language :: Python :: 3
Classifier: License :: OSI Approved :: MIT License
Classifier: Operating System :: OS Independent
Requires-Python: >=3.9
License-File: LICENSE.txt
Requires-Dist: matplotlib>=3.7.2
Requires-Dist: numpy>=1.25.1
Requires-Dist: setuptools>=65.5.0
Requires-Dist: scipy>=1.11.2
Requires-Dist: pytest>=7.4.2
Requires-Dist: black>=23.11.0
Requires-Dist: pillow>=10.3.0
Requires-Dist: pyparsing>=3.1.2
Requires-Dist: python-dateutil>=2.9.0.post0
Requires-Dist: scipy>=1.13.0
Requires-Dist: six>=1.16.0
Requires-Dist: cupy-cuda12x>=13.0.0
